README.md
setup.cfg
setup.py
salt_sit.egg-info/PKG-INFO
salt_sit.egg-info/SOURCES.txt
salt_sit.egg-info/dependency_links.txt
salt_sit.egg-info/requires.txt
salt_sit.egg-info/top_level.txt
sit/__init__.py
sit/check_sit.py
sit/ecs_container.py
sit/launch_review_job.py
sit/redis_client.py