Metadata-Version: 1.0
Name: salt-sit
Version: 0.0.3
Summary: Salt Integration Testing Tool -- applies role configurations to Docker container minions using AWS (Amazon Web Services) ECS (EC2 Container Service)
Home-page: https://github.com/dandb/salt-integration-testing
Author: Dun and Bradstreet
Author-email: sit.dandb@gmail.com
License: GPLv3
Keywords: Salt SaltStack Roles Test Docker AWS EC2 AutoScale AutoScaling Group ECS EC2 Container Service Integration Testing
Platform: UNKNOWN
